thermoworks_smoke/__init__.py
thermoworks_smoke/__main__.py
thermoworks_smoke/thermoworks_smoke.py
thermoworks_smoke-0.1.8.dist-info/LICENSE
thermoworks_smoke-0.1.8.dist-info/METADATA
thermoworks_smoke-0.1.8.dist-info/WHEEL
thermoworks_smoke-0.1.8.dist-info/top_level.txt
thermoworks_smoke-0.1.8.dist-info/RECORD
