Metadata-Version: 2.1
Name: thermoworks-smoke
Version: 0.1.8
Summary: Pull data for your thermoworks smoke thermometer
Home-page: https://github.com/nhorvath/python-thermoworks-smoke
Author: nhorvath
Author-email: nhorvath@gmail.com
License: GPLv3
Keywords: Thermoworks
Platform: UNKNOWN
Classifier: Development Status :: 3 - Alpha
Classifier: Intended Audience :: Developers
Classifier: License :: OSI Approved :: GNU General Public License v3 (GPLv3)
Classifier: Programming Language :: Python :: 3
Requires-Dist: pyrebase4 (>=4.3.0)
